[
    {
        "name": "BMW X5, 2017",
        "description": "3.0 л (249 л.с.),дизель,АКПП,4WD,76 000 км",
        "price": "5 350 000 ₽"
    },
    {
        "name": "BMW X5, 2017",
        "description": "3.0 л (313 л.с.),дизель,АКПП,4WD,130 000 км",
        "price": "5 195 223 ₽"
    },
    {
        "name": "BMW X5, 2023",
        "description": "3.0 л (352 л.с.),гибрид,гибридавтомат,4WD",
        "price": "15 490 000 ₽"
    },
    {
        "name": "BMW X5, 2011",
        "description": "3.0 л (306 л.с.),бензин,АКПП,4WD,290 000 км",
        "price": "2 250 000 ₽"
    },
    {
        "name": "BMW X5, 2023",
        "description": "3.0 л (298 л.с.),дизель,АКПП,4WD",
        "price": "13 290 000 ₽"
    }
]